midas_powergrid/__init__.py
midas_powergrid/meta.py
midas_powergrid/module.py
midas_powergrid/plotter.py
midas_powergrid/simulator.py
midas_powergrid/analysis/__init__.py
midas_powergrid/analysis/bus.py
midas_powergrid/analysis/grid.py
midas_powergrid/analysis/power.py
midas_powergrid/constraints/__init__.py
midas_powergrid/constraints/base.py
midas_powergrid/constraints/line_loading.py
midas_powergrid/constraints/load_voltage_change.py
midas_powergrid/constraints/sgen_voltage_change.py
midas_powergrid/constraints/tap_changes.py
midas_powergrid/constraints/voltage_band.py
midas_powergrid/constraints/voltage_change.py
midas_powergrid/custom/__init__.py
midas_powergrid/custom/bhv.py
midas_powergrid/custom/midaslv.py
midas_powergrid/custom/midasmv.py
midas_powergrid/elements/__init__.py
midas_powergrid/elements/base.py
midas_powergrid/elements/bus.py
midas_powergrid/elements/line.py
midas_powergrid/elements/load.py
midas_powergrid/elements/sgen.py
midas_powergrid/elements/switch.py
midas_powergrid/elements/transformer.py
midas_powergrid/model/__init__.py
midas_powergrid/model/pp_grid.py
midas_powergrid/model/static.py
midas_powergrid/model/surrogate.py
midas_powergrid-2.0.10.dist-info/licenses/LICENSE
midas_powergrid-2.0.10.dist-info/METADATA
midas_powergrid-2.0.10.dist-info/WHEEL
midas_powergrid-2.0.10.dist-info/top_level.txt
midas_powergrid-2.0.10.dist-info/RECORD
