Metadata-Version: 2.4
Name: midas-powergrid
Version: 2.0.10
Summary: A simulator for pandapower grids.
Author-email: Stephan Balduin <stephan.balduin@offis.de>
Project-URL: Documentation, https://midas-mosaik.gitlab.io/midas
Requires-Python: >=3.8
License-File: LICENSE
Requires-Dist: midas-mosaik~=2.0.0
Requires-Dist: mosaik_api
Requires-Dist: numpy
Requires-Dist: matplotlib
Requires-Dist: pandapower
Requires-Dist: lightsim2grid
Requires-Dist: numba
Requires-Dist: simbench
Requires-Dist: natsort
Requires-Dist: joblib
Dynamic: license-file
